scraper/__init__.py
scraper/server.py
doc_scraper_mcp_server-0.1.2.dist-info/METADATA
doc_scraper_mcp_server-0.1.2.dist-info/WHEEL
doc_scraper_mcp_server-0.1.2.dist-info/entry_points.txt
doc_scraper_mcp_server-0.1.2.dist-info/top_level.txt
doc_scraper_mcp_server-0.1.2.dist-info/RECORD
