Metadata-Version: 2.4
Name: doc-scraper-mcp-server
Version: 0.1.2
Summary: Add your description here
Requires-Python: >=3.13
Requires-Dist: aiohttp>=3.8.0
Requires-Dist: certifi>=2025.1.31
Requires-Dist: mcp>=0.1.0
Requires-Dist: pydantic>=1.10.0
